skaiciuotuvas/__init__.py
skaiciuotuvas/skaiciuotuvas.py
skaiciuotuvas-1.0.dist-info/METADATA
skaiciuotuvas-1.0.dist-info/WHEEL
skaiciuotuvas-1.0.dist-info/top_level.txt
skaiciuotuvas-1.0.dist-info/RECORD
