Metadata-Version: 2.1
Name: skaiciuotuvas
Version: 1.0
Summary: calculator
Home-page: https://www.linkedin.com/in/mindaugas-vokietis-0584197/
Author: metacount
Author-email: mindaugas.vokietis@gmail.com
Requires-Python: >=3.6
